{
  "title": "Innovative Digital Solutions",
  "liveDemo": "Live Demo",
  "sourceCode": "Source Code",
  "items": [
    {
      "id": "1",
      "title": "Professional Portfolio",
      "description": "A modern, interactive portfolio website built with Next.js, React, TailwindCSS, and shadcn/ui.",
      "image": "https://images.unsplash.com/photo-1515879218367-8466d910aaa4?q=80&w=1600&auto=format&fit=crop",
      "techStack": ["Next.js", "React", "TailwindCSS", "shadcn/ui", "Framer Motion"],
      "projectUrl": "https://example.com/portfolio",
      "github": "https://github.com/kholik-3/portfolio-kholik-3",
      "featured": true
    },
    {
      "id": "2",
      "title": "E-Commerce Dashboard",
      "description": "A comprehensive dashboard for managing an e-commerce platform, including sales tracking and inventory management.",
      "image": "https://images.unsplash.com/photo-1551288049-bebda4e38f71?q=80&w=1600&auto=format&fit=crop",
      "techStack": ["Next.js", "TanStack Query", "Prisma", "PostgreSQL"],
      "projectUrl": "https://example.com/dashboard",
      "github": null,
      "featured": false
    },
    {
      "id": "3",
      "title": "Analytics Workspace",
      "description": "A data analytics workspace for insights, reporting, and KPI monitoring across teams.",
      "image": "https://images.unsplash.com/photo-1556155092-8707de31f9c4?q=80&w=1600&auto=format&fit=crop",
      "techStack": ["React", "TypeScript", "Node.js", "PostgreSQL"],
      "projectUrl": "https://example.com/analytics",
      "github": "https://github.com/kholik-3/analytics-workspace",
      "featured": true
    }
  ]
}
